nav2_client/__init__.py
nav2_client/cli_client.py
nav2_client/native_client.py
nav2_client/nav2_client.py
nav2_client/utils.py
ros2_client/__init__.py
ros2_client/cli_client.py
ros2_client/native_client.py
ros2_client/ros2_client.py
ros2_client/utils.py
ros2_robotframework-1.0.1.dist-info/licenses/LICENSE
ros2_robotframework-1.0.1.dist-info/METADATA
ros2_robotframework-1.0.1.dist-info/WHEEL
ros2_robotframework-1.0.1.dist-info/entry_points.txt
ros2_robotframework-1.0.1.dist-info/top_level.txt
ros2_robotframework-1.0.1.dist-info/RECORD
