Metadata-Version: 2.4
Name: ros2-robotframework
Version: 1.0.1
Summary: A comprehensive Robot Framework library for ROS2 operations
Author-email: ROS2 Robot Framework Team <bekirbostanci@gmail.com>
Maintainer-email: ROS2 Robot Framework Team <bekirbostanci@gmail.com>
License-Expression: Apache-2.0
Project-URL: Homepage, https://github.com/bekirbostanci/ros2_robotframework
Project-URL: Repository, https://github.com/bekirbostanci/ros2_robotframework
Project-URL: Documentation, https://github.com/bekirbostanci/ros2_robotframework#readme
Project-URL: Bug Reports, https://github.com/bekirbostanci/ros2_robotframework/issues
Project-URL: Changelog, https://github.com/bekirbostanci/ros2_robotframework/blob/main/CHANGELOG.md
Keywords: robotframework,ros2,robotics,testing,automation
Classifier: Development Status :: 3 - Alpha
Classifier: Intended Audience :: Developers
Classifier: Operating System :: OS Independent
Classifier: Programming Language :: Python :: 3
Classifier: Programming Language :: Python :: 3.8
Classifier: Programming Language :: Python :: 3.9
Classifier: Programming Language :: Python :: 3.10
Classifier: Programming Language :: Python :: 3.11
Classifier: Programming Language :: Python :: 3.12
Classifier: Topic :: Software Development :: Testing
Classifier: Topic :: Scientific/Engineering :: Artificial Intelligence
Requires-Python: >=3.8
License-File: LICENSE
Requires-Dist: robotframework>=6.0.0
Requires-Dist: rclpy>=3.0.0
Requires-Dist: std-msgs
Requires-Dist: geometry-msgs
Requires-Dist: sensor-msgs
Requires-Dist: nav-msgs
Requires-Dist: tf2-msgs
Requires-Dist: tf2-geometry-msgs
Requires-Dist: action-msgs
Requires-Dist: lifecycle-msgs
Requires-Dist: numpy
Requires-Dist: typing-extensions
Requires-Dist: PyYAML>=6.0
Requires-Dist: setuptools>=61.0
Provides-Extra: dev
Requires-Dist: pytest>=6.0; extra == "dev"
Requires-Dist: pytest-cov>=2.0; extra == "dev"
Requires-Dist: black>=21.0; extra == "dev"
Requires-Dist: flake8>=3.8; extra == "dev"
Requires-Dist: mypy>=0.800; extra == "dev"
Requires-Dist: pre-commit>=2.0; extra == "dev"
Provides-Extra: nav2
Requires-Dist: nav2-msgs; extra == "nav2"
Requires-Dist: nav2-common; extra == "nav2"
Provides-Extra: test
Requires-Dist: pytest>=6.0; extra == "test"
Requires-Dist: pytest-cov>=2.0; extra == "test"
Requires-Dist: pytest-mock>=3.0; extra == "test"
Provides-Extra: docs
Requires-Dist: sphinx>=4.0; extra == "docs"
Requires-Dist: sphinx-rtd-theme>=1.0; extra == "docs"
Requires-Dist: myst-parser>=0.18; extra == "docs"
Dynamic: license-file
